Workbook

Sheet Tableau de bord
A1: Multimédia Glory Guinée SARLU
A2: Tableau de bord — Responsable administratif
A3: Chiffres d’exemple : remplacez les cellules jaunes des feuilles Indicateurs et Missions par vos données. Tout le reste se calcule.
A4: SYNTHÈSE
B5: Atteint | C5: À surveiller | D5: Hors cible | E5: À renseigner | F5: Total | G5: Part atteinte
A6: Indicateurs | B6: =COUNTIF(Indicateurs!$H$6:$H$16,B$5) -> 5 | C6: =COUNTIF(Indicateurs!$H$6:$H$16,C$5) -> 4 | D6: =COUNTIF(Indicateurs!$H$6:$H$16,D$5) -> 2 | E6: =COUNTIF(Indicateurs!$H$6:$H$16,E$5) -> 0 | F6: =SUM(B6:E6) -> 11 | G6: =IF(F6=0,0,B6/F6) -> 0.45454545
B7: Fait | C7: En cours | D7: Bloquée | E7: À faire | F7: Total | G7: Part faite
A8: Missions de la période | B8: =COUNTIF(Missions!$H$5:$H$21,B$7) -> 8 | C8: =COUNTIF(Missions!$H$5:$H$21,C$7) -> 4 | D8: =COUNTIF(Missions!$H$5:$H$21,D$7) -> 2 | E8: =COUNTIF(Missions!$H$5:$H$21,E$7) -> 3 | F8: =SUM(B8:E8) -> 17 | G8: =IF(F8=0,0,B8/F8) -> 0.47058824
A10: PAR DOMAINE
A11: Domaine | B11: Missions | C11: Fait | D11: En cours | E11: Bloquée | F11: À faire | G11: Part faite | H11: Indicateurs hors cible | I11: Indicateurs à surveiller
A12: Gestion administrative | B12: =COUNTIF(Missions!$B$5:$B$21,$A12) -> 2 | C12: =COUNTIFS(Missions!$B$5:$B$21,$A12,Missions!$H$5:$H$21,C$11) -> 2 | D12: =COUNTIFS(Missions!$B$5:$B$21,$A12,Missions!$H$5:$H$21,D$11) -> 0 | E12: =COUNTIFS(Missions!$B$5:$B$21,$A12,Missions!$H$5:$H$21,E$11) -> 0 | F12: =COUNTIFS(Missions!$B$5:$B$21,$A12,Missions!$H$5:$H$21,F$11) -> 0 | G12: =IF($B12=0,0,C12/$B12) -> 1 | H12: =COUNTIFS(Indicateurs!$A$6:$A$16,$A12,Indicateurs!$H$6:$H$16,"Hors cible") -> 0 | I12: =COUNTIFS(Indicateurs!$A$6:$A$16,$A12,Indicateurs!$H$6:$H$16,"À surveiller") -> 2
A13: Conventions, avenants et contrats | B13: =COUNTIF(Missions!$B$5:$B$21,$A13) -> 3 | C13: =COUNTIFS(Missions!$B$5:$B$21,$A13,Missions!$H$5:$H$21,C$11) -> 2 | D13: =COUNTIFS(Missions!$B$5:$B$21,$A13,Missions!$H$5:$H$21,D$11) -> 1 | E13: =COUNTIFS(Missions!$B$5:$B$21,$A13,Missions!$H$5:$H$21,E$11) -> 0 | F13: =COUNTIFS(Missions!$B$5:$B$21,$A13,Missions!$H$5:$H$21,F$11) -> 0 | G13: =IF($B13=0,0,C13/$B13) -> 0.66666667 | H13: =COUNTIFS(Indicateurs!$A$6:$A$16,$A13,Indicateurs!$H$6:$H$16,"Hors cible") -> 1 | I13: =COUNTIFS(Indicateurs!$A$6:$A$16,$A13,Indicateurs!$H$6:$H$16,"À surveiller") -> 0
A14: Relations avec les partenaires | B14: =COUNTIF(Missions!$B$5:$B$21,$A14) -> 3 | C14: =COUNTIFS(Missions!$B$5:$B$21,$A14,Missions!$H$5:$H$21,C$11) -> 1 | D14: =COUNTIFS(Missions!$B$5:$B$21,$A14,Missions!$H$5:$H$21,D$11) -> 1 | E14: =COUNTIFS(Missions!$B$5:$B$21,$A14,Missions!$H$5:$H$21,E$11) -> 1 | F14: =COUNTIFS(Missions!$B$5:$B$21,$A14,Missions!$H$5:$H$21,F$11) -> 0 | G14: =IF($B14=0,0,C14/$B14) -> 0.33333333 | H14: =COUNTIFS(Indicateurs!$A$6:$A$16,$A14,Indicateurs!$H$6:$H$16,"Hors cible") -> 0 | I14: =COUNTIFS(Indicateurs!$A$6:$A$16,$A14,Indicateurs!$H$6:$H$16,"À surveiller") -> 1
A15: Contrôle et suivi financier | B15: =COUNTIF(Missions!$B$5:$B$21,$A15) -> 5 | C15: =COUNTIFS(Missions!$B$5:$B$21,$A15,Missions!$H$5:$H$21,C$11) -> 1 | D15: =COUNTIFS(Missions!$B$5:$B$21,$A15,Missions!$H$5:$H$21,D$11) -> 1 | E15: =COUNTIFS(Missions!$B$5:$B$21,$A15,Missions!$H$5:$H$21,E$11) -> 1 | F15: =COUNTIFS(Missions!$B$5:$B$21,$A15,Missions!$H$5:$H$21,F$11) -> 2 | G15: =IF($B15=0,0,C15/$B15) -> 0.2 | H15: =COUNTIFS(Indicateurs!$A$6:$A$16,$A15,Indicateurs!$H$6:$H$16,"Hors cible") -> 1 | I15: =COUNTIFS(Indicateurs!$A$6:$A$16,$A15,Indicateurs!$H$6:$H$16,"À surveiller") -> 1
A16: Pilotage de l’équipe | B16: =COUNTIF(Missions!$B$5:$B$21,$A16) -> 3 | C16: =COUNTIFS(Missions!$B$5:$B$21,$A16,Missions!$H$5:$H$21,C$11) -> 2 | D16: =COUNTIFS(Missions!$B$5:$B$21,$A16,Missions!$H$5:$H$21,D$11) -> 0 | E16: =COUNTIFS(Missions!$B$5:$B$21,$A16,Missions!$H$5:$H$21,E$11) -> 0 | F16: =COUNTIFS(Missions!$B$5:$B$21,$A16,Missions!$H$5:$H$21,F$11) -> 1 | G16: =IF($B16=0,0,C16/$B16) -> 0.66666667 | H16: =COUNTIFS(Indicateurs!$A$6:$A$16,$A16,Indicateurs!$H$6:$H$16,"Hors cible") -> 0 | I16: =COUNTIFS(Indicateurs!$A$6:$A$16,$A16,Indicateurs!$H$6:$H$16,"À surveiller") -> 0
A17: Demandes de la Direction | B17: =COUNTIF(Missions!$B$5:$B$21,$A17) -> 1 | C17: =COUNTIFS(Missions!$B$5:$B$21,$A17,Missions!$H$5:$H$21,C$11) -> 0 | D17: =COUNTIFS(Missions!$B$5:$B$21,$A17,Missions!$H$5:$H$21,D$11) -> 1 | E17: =COUNTIFS(Missions!$B$5:$B$21,$A17,Missions!$H$5:$H$21,E$11) -> 0 | F17: =COUNTIFS(Missions!$B$5:$B$21,$A17,Missions!$H$5:$H$21,F$11) -> 0 | G17: =IF($B17=0,0,C17/$B17) -> 0 | H17: =COUNTIFS(Indicateurs!$A$6:$A$16,$A17,Indicateurs!$H$6:$H$16,"Hors cible") -> 0 | I17: =COUNTIFS(Indicateurs!$A$6:$A$16,$A17,Indicateurs!$H$6:$H$16,"À surveiller") -> 0
A18: Total | B18: =SUM(B12:B17) -> 17 | C18: =SUM(C12:C17) -> 8 | D18: =SUM(D12:D17) -> 4 | E18: =SUM(E12:E17) -> 2 | F18: =SUM(F12:F17) -> 3 | G18: =IF(B18=0,0,C18/B18) -> 0.47058824 | H18: =SUM(H12:H17) -> 2 | I18: =SUM(I12:I17) -> 4
A40: Hypothèses : rythmes, indicateurs, cibles et marges sont des propositions à valider. Les statuts et chiffres affichés au départ sont des exemples.

Sheet Indicateurs
A1: Multimédia Glory Guinée SARLU — Indicateurs de pilotage
A2: Saisissez la cible et le réalisé (cellules jaunes) : l’écart et l’état se calculent seuls. Chiffres actuels : exemples.
A3: Seuil « À surveiller » (cibles à atteindre ≥) | C3: 0.9 | D3: Part minimale de la cible pour rester « À surveiller » (hypothèse proposée, modifiable)
A5: Domaine | B5: Indicateur | C5: Sens | D5: Marge « à surveiller » (plafonds seulement) | E5: Cible | F5: Réalisé | G5: Écart | H5: État
A6: Gestion administrative | B6: Dossiers traités dans les délais | C6: ≥ | E6: 0.95 | F6: 0.92 | G6: =IF(OR(E6="",F6=""),"",F6-E6) -> -0.03 | H6: =IF(OR(E6="",F6=""),"À renseigner",IF(C6="≥",IF(F6>=E6,"Atteint",IF(F6>=E6*$C$3,"À surveiller","Hors cible")),IF(F6<=E6,"Atteint",IF(F6<=E6+D6,"À surveiller","Hors cible")))) -> À surveiller
A7: Gestion administrative | B7: Courriers et dossiers en retard | C7: ≤ | D7: 3 | E7: 2 | F7: 4 | G7: =IF(OR(E7="",F7=""),"",F7-E7) -> 2 | H7: =IF(OR(E7="",F7=""),"À renseigner",IF(C7="≥",IF(F7>=E7,"Atteint",IF(F7>=E7*$C$3,"À surveiller","Hors cible")),IF(F7<=E7,"Atteint",IF(F7<=E7+D7,"À surveiller","Hors cible")))) -> À surveiller
A8: Conventions, avenants et contrats | B8: Conventions saisies dans le suivi | C8: ≥ | E8: 1 | F8: 1 | G8: =IF(OR(E8="",F8=""),"",F8-E8) -> 0 | H8: =IF(OR(E8="",F8=""),"À renseigner",IF(C8="≥",IF(F8>=E8,"Atteint",IF(F8>=E8*$C$3,"À surveiller","Hors cible")),IF(F8<=E8,"Atteint",IF(F8<=E8+D8,"À surveiller","Hors cible")))) -> Atteint
A9: Conventions, avenants et contrats | B9: Documents échus sans suite | C9: ≤ | D9: 1 | E9: 0 | F9: 2 | G9: =IF(OR(E9="",F9=""),"",F9-E9) -> 2 | H9: =IF(OR(E9="",F9=""),"À renseigner",IF(C9="≥",IF(F9>=E9,"Atteint",IF(F9>=E9*$C$3,"À surveiller","Hors cible")),IF(F9<=E9,"Atteint",IF(F9<=E9+D9,"À surveiller","Hors cible")))) -> Hors cible
A10: Relations avec les partenaires | B10: Envois complets du premier coup | C10: ≥ | E10: 0.98 | F10: 0.96 | G10: =IF(OR(E10="",F10=""),"",F10-E10) -> -0.02 | H10: =IF(OR(E10="",F10=""),"À renseigner",IF(C10="≥",IF(F10>=E10,"Atteint",IF(F10>=E10*$C$3,"À surveiller","Hors cible")),IF(F10<=E10,"Atteint",IF(F10<=E10+D10,"À surveiller","Hors cible")))) -> À surveiller
A11: Relations avec les partenaires | B11: Demandes de partenaires sans réponse | C11: ≤ | D11: 2 | E11: 0 | F11: 0 | G11: =IF(OR(E11="",F11=""),"",F11-E11) -> 0 | H11: =IF(OR(E11="",F11=""),"À renseigner",IF(C11="≥",IF(F11>=E11,"Atteint",IF(F11>=E11*$C$3,"À surveiller","Hors cible")),IF(F11<=E11,"Atteint",IF(F11<=E11+D11,"À surveiller","Hors cible")))) -> Atteint
A12: Contrôle et suivi financier | B12: Anomalies de saisie non corrigées | C12: ≤ | D12: 2 | E12: 0 | F12: 0 | G12: =IF(OR(E12="",F12=""),"",F12-E12) -> 0 | H12: =IF(OR(E12="",F12=""),"À renseigner",IF(C12="≥",IF(F12>=E12,"Atteint",IF(F12>=E12*$C$3,"À surveiller","Hors cible")),IF(F12<=E12,"Atteint",IF(F12<=E12+D12,"À surveiller","Hors cible")))) -> Atteint
A13: Contrôle et suivi financier | B13: Justificatifs classés | C13: ≥ | E13: 1 | F13: 0.97 | G13: =IF(OR(E13="",F13=""),"",F13-E13) -> -0.03 | H13: =IF(OR(E13="",F13=""),"À renseigner",IF(C13="≥",IF(F13>=E13,"Atteint",IF(F13>=E13*$C$3,"À surveiller","Hors cible")),IF(F13<=E13,"Atteint",IF(F13<=E13+D13,"À surveiller","Hors cible")))) -> À surveiller
A14: Contrôle et suivi financier | B14: Règlements en retard | C14: ≤ | D14: 2 | E14: 0 | F14: 3 | G14: =IF(OR(E14="",F14=""),"",F14-E14) -> 3 | H14: =IF(OR(E14="",F14=""),"À renseigner",IF(C14="≥",IF(F14>=E14,"Atteint",IF(F14>=E14*$C$3,"À surveiller","Hors cible")),IF(F14<=E14,"Atteint",IF(F14<=E14+D14,"À surveiller","Hors cible")))) -> Hors cible
A15: Pilotage de l’équipe | B15: Objectifs de l’équipe atteints | C15: ≥ | E15: 0.9 | F15: 0.9 | G15: =IF(OR(E15="",F15=""),"",F15-E15) -> 0 | H15: =IF(OR(E15="",F15=""),"À renseigner",IF(C15="≥",IF(F15>=E15,"Atteint",IF(F15>=E15*$C$3,"À surveiller","Hors cible")),IF(F15<=E15,"Atteint",IF(F15<=E15+D15,"À surveiller","Hors cible")))) -> Atteint
A16: Demandes de la Direction | B16: Demandes de la Direction traitées dans les délais | C16: ≥ | E16: 1 | F16: 1 | G16: =IF(OR(E16="",F16=""),"",F16-E16) -> 0 | H16: =IF(OR(E16="",F16=""),"À renseigner",IF(C16="≥",IF(F16>=E16,"Atteint",IF(F16>=E16*$C$3,"À surveiller","Hors cible")),IF(F16<=E16,"Atteint",IF(F16<=E16+D16,"À surveiller","Hors cible")))) -> Atteint
A18: Lecture :
A19: • Sens ≥ : la cible est un minimum. Atteint si le réalisé la respecte ; À surveiller si le réalisé atteint au moins le seuil ci-dessus (C3) de la cible ; sinon Hors cible.
A20: • Sens ≤ : la cible est un plafond (retards, anomalies…). Atteint si le réalisé reste sous le plafond ; À surveiller jusqu’à la marge de la colonne D au-dessus ; sinon Hors cible.
A21: • Les pourcentages sont saisis en % (92 % ou 0,92). L’écart des pourcentages se lit en points.
A22: • Cibles, marges et chiffres réalisés sont des exemples proposés : remplacez-les par vos objectifs réels.

Sheet Missions
A1: Multimédia Glory Guinée SARLU — Missions du responsable administratif
A2: Choisissez le statut de la période dans la colonne H (liste déroulante). Statuts actuels : exemples.
A3: Rythmes et indicateurs associés : propositions à adapter. Seules les missions et le rythme mensuel de la saisie et des tableaux de bord viennent des termes de référence.
A4: ID | B4: Domaine | C4: Mission | D4: Détail | E4: Rythme * | F4: Catégorie de rythme | G4: Indicateur associé * | H4: Statut de la période
A5: g1 | B5: Gestion administrative | C5: Assurer la bonne gestion administrative de l’entreprise | E5: Continu | F5: Continu | G5: Dossiers et courriers en retard (nombre) | H5: Fait
A6: g2 | B6: Gestion administrative | C6: Traiter les dossiers administratifs | D6: Prise de rendez-vous, rédaction du courrier, classement des dossiers, saisie de documents ou du budget | E6: Quotidien | F6: Quotidien | G6: Dossiers traités dans les délais (%) | H6: Fait
A7: c1 | B7: Conventions, avenants et contrats | C7: Assurer la bonne gestion des conventions, des avenants et des contrats | E7: Continu | F7: Continu | G7: Documents échus sans suite (nombre) | H7: Fait
A8: c2 | B8: Conventions, avenants et contrats | C8: Enregistrer et conserver les conventions, les avenants et les contrats | E8: À chaque signature | F8: À chaque événement | G8: Documents archivés sur documents signés (%) | H8: Fait
A9: c3 | B9: Conventions, avenants et contrats | C9: Saisir les conventions pour leur suivi | E9: À chaque convention | F9: À chaque événement | G9: Conventions saisies dans le suivi (%) | H9: En cours
A10: p1 | B10: Relations avec les partenaires | C10: Assurer les relations administratives avec les différents partenaires | E10: Continu | F10: Continu | G10: Demandes sans réponse (nombre) | H10: Fait
A11: p2 | B11: Relations avec les partenaires | C11: Recenser les documents à transmettre | D11: Protocole, émargements, conventions… | E11: Mensuel | F11: Mensuel | G11: Documents recensés sur documents attendus (%) | H11: En cours
A12: p3 | B12: Relations avec les partenaires | C12: Contrôler l’ensemble des pièces avant envoi | E12: Avant chaque envoi | F12: À chaque événement | G12: Envois complets du premier coup (%) | H12: Bloquée
A13: k1 | B13: Contrôle et suivi financier | C13: Contrôler les différents documents administratifs | E13: Hebdomadaire | F13: Hebdomadaire | G13: Documents non conformes relevés (nombre) | H13: Fait
A14: k2 | B14: Contrôle et suivi financier | C14: Vérifier la saisie mensuelle | D14: Anomalies, cohérence des plannings | E14: Mensuel | F14: Mensuel | G14: Anomalies de saisie non corrigées (nombre) | H14: En cours
A15: k3 | B15: Contrôle et suivi financier | C15: Classer les documents justificatifs | E15: Hebdomadaire | F15: Hebdomadaire | G15: Justificatifs classés (%) | H15: À faire
A16: k4 | B16: Contrôle et suivi financier | C16: Établir les tableaux de bord mensuels | D16: En lien avec le cadre intermédiaire financier | E16: Mensuel | F16: Mensuel | G16: Tableau remis dans les délais (oui / non) | H16: À faire
A17: k5 | B17: Contrôle et suivi financier | C17: Suivre les règlements | E17: Hebdomadaire | F17: Hebdomadaire | G17: Règlements en retard (nombre) | H17: Bloquée
A18: e1 | B18: Pilotage de l’équipe | C18: Piloter l’équipe administrative | E18: Hebdomadaire | F18: Hebdomadaire | G18: Objectifs de l’équipe atteints (%) | H18: Fait
A19: e2 | B19: Pilotage de l’équipe | C19: Veiller au bon fonctionnement de l’équipe | E19: Continu | F19: Continu | G19: Points de blocage ouverts (nombre) | H19: À faire
A20: e3 | B20: Pilotage de l’équipe | C20: Coordonner le travail auprès de ses collaborateurs | E20: Quotidien | F20: Quotidien | G20: Tâches réparties et suivies (%) | H20: Fait
A21: d1 | B21: Demandes de la Direction | C21: Accomplir toutes autres tâches confiées par le Directeur Général | E21: Sur demande | F21: À chaque événement | G21: Demandes traitées dans les délais (%) | H21: En cours
A23: Une mission récurrente n’est jamais « terminée » : « Fait » veut dire fait pour la période en cours. À chaque nouvelle période, remettez la colonne H sur « À faire ».

Sheet Termes de référence
A1: Multimédia Glory Guinée SARLU — Termes de référence expliqués — Responsable administratif
A2: Texte du document d’origine (orthographe corrigée), puis explication simple de chaque ligne. La colonne C indique où la ligne est suivie dans le classeur.
A3: Quand le texte dit « assurer », « veiller » ou « piloter », le responsable répond du résultat, même s’il ne fait pas tout lui-même. Quand il dit « saisir », « classer » ou « enregistrer », c’est une tâche qu’il fait lui-même.
A5: Fonction (texte du document) | B5: Mission suivie (ID) | C5: Domaine suivi | D5: En simple | E5: Concrètement | F5: C’est bien fait quand | G5: À savoir
A6: Assurer la bonne gestion administrative de l’entreprise | B6: g1 | C6: =IF(B6="","Rôle du poste",IFERROR(INDEX(Missions!$B$5:$B$21,MATCH(B6,Missions!$A$5:$A$21,0)),"ID inconnu")) -> Gestion administrative | D6: Faire en sorte que l’administration fonctionne bien au quotidien : à jour, organisée, sans retard. | E6: • Fixer des règles claires : qui fait quoi, où ranger, quels délais. • Repérer ce qui traîne et le corriger. | F6: Il y a peu de retards et on retrouve vite n’importe quel dossier.
A7: Assurer la bonne gestion des conventions, des avenants et des contrats | B7: c1 | C7: =IF(B7="","Rôle du poste",IFERROR(INDEX(Missions!$B$5:$B$21,MATCH(B7,Missions!$A$5:$A$21,0)),"ID inconnu")) -> Conventions, avenants et contrats | D7: S’assurer qu’aucun accord n’est perdu, oublié ou expiré sans que personne ne s’en aperçoive. | E7: • Tenir la liste de tous les accords : partenaire, dates de début et de fin, montant. • Prévenir la direction avant chaque échéance. • Préparer les renouvellements et les avenants. | F7: Aucun document n’arrive à échéance sans qu’une décision ait été prise. | G7: Lexique : Convention : accord écrit avec un partenaire. Contrat : accord qui engage l’entreprise. Avenant : document qui modifie un accord existant.
A8: Enregistrer et conserver les conventions, les avenants et les contrats | B8: c2 | C8: =IF(B8="","Rôle du poste",IFERROR(INDEX(Missions!$B$5:$B$21,MATCH(B8,Missions!$A$5:$A$21,0)),"ID inconnu")) -> Conventions, avenants et contrats | D8: Garder une trace officielle et en sécurité de chaque accord. | E8: • Enregistrer : noter l’accord dans un registre (numéro, date, partenaire). • Conserver : archiver la version signée, en papier et en scan, bien rangée et sauvegardée. | F8: On retrouve un contrat signé en quelques minutes.
A9: Assurer les relations administratives avec les différents partenaires | B9: p1 | C9: =IF(B9="","Rôle du poste",IFERROR(INDEX(Missions!$B$5:$B$21,MATCH(B9,Missions!$A$5:$A$21,0)),"ID inconnu")) -> Relations avec les partenaires | D9: Être l’interlocuteur administratif des partenaires, pas celui qui négocie les accords. | E9: • Répondre à leurs demandes et leur envoyer les documents. • Relancer quand il manque quelque chose. • Garder une trace des échanges. | F9: Aucune demande de partenaire ne reste sans réponse.
A10: Recenser les documents à transmettre (protocole, émargements, conventions, …) | B10: p2 | C10: =IF(B10="","Rôle du poste",IFERROR(INDEX(Missions!$B$5:$B$21,MATCH(B10,Missions!$A$5:$A$21,0)),"ID inconnu")) -> Relations avec les partenaires | D10: Faire la liste de tout ce qu’il faut envoyer à chaque partenaire, et vérifier qu’on l’a bien. | E10: • Comparer ce qui est attendu avec ce qui est reçu. • Relancer les documents manquants. | F10: La liste est complète et rien n’est oublié au moment d’envoyer. | G10: Lexique : Protocole : document qui fixe les règles de collaboration. Émargements : feuilles de présence signées par les personnes présentes à une séance, une formation ou une activité.
A11: Saisir les conventions pour leur suivi | B11: c3 | C11: =IF(B11="","Rôle du poste",IFERROR(INDEX(Missions!$B$5:$B$21,MATCH(B11,Missions!$A$5:$A$21,0)),"ID inconnu")) -> Conventions, avenants et contrats | D11: Copier les informations clés de chaque convention dans le fichier ou le logiciel de suivi. | E11: • Noter les dates, les montants et ce que chaque partie doit fournir. • C’est ce qui permet de savoir à tout moment où en est chaque convention. | F11: Toutes les conventions sont dans l’outil de suivi, avec des informations exactes. | G11: À ne pas confondre : Différence avec « Enregistrer et conserver » : l’enregistrement sert à archiver, la saisie sert à suivre.
A12: Contrôler l’ensemble des pièces avant envoi | B12: p3 | C12: =IF(B12="","Rôle du poste",IFERROR(INDEX(Missions!$B$5:$B$21,MATCH(B12,Missions!$A$5:$A$21,0)),"ID inconnu")) -> Relations avec les partenaires | D12: C’est la dernière vérification avant de transmettre un dossier. | E12: • Vérifier que tout est présent, signé et lisible. • Vérifier que les noms, les dates et les montants sont justes. • Une pièce manquante peut bloquer un paiement ou retarder un dossier. | F12: Les dossiers sont acceptés du premier coup, sans demande de complément.
A13: Contrôler les différents documents administratifs | B13: k1 | C13: =IF(B13="","Rôle du poste",IFERROR(INDEX(Missions!$B$5:$B$21,MATCH(B13,Missions!$A$5:$A$21,0)),"ID inconnu")) -> Contrôle et suivi financier | D13: Relire les documents pour s’assurer qu’ils sont corrects et conformes. | E13: • Vérifier les signatures, les dates et les mentions obligatoires. • Vérifier que les documents ne se contredisent pas entre eux. | F13: Peu d’erreurs passent entre les mailles.
A14: Vérifier la saisie mensuelle (anomalie, cohérence des plannings) | B14: k2 | C14: =IF(B14="","Rôle du poste",IFERROR(INDEX(Missions!$B$5:$B$21,MATCH(B14,Missions!$A$5:$A$21,0)),"ID inconnu")) -> Contrôle et suivi financier | D14: Chaque mois, relire ce qui a été saisi pour repérer les erreurs. | E14: • Une anomalie est une erreur, un doublon, un oubli ou un montant qui paraît étrange. • La cohérence des plannings veut dire que les horaires, les présences et les affectations correspondent à la réalité : une personne ne peut pas être à deux endroits à la fois. • Cette saisie sert souvent à payer ou à facturer, d’où l’importance de la vérifier. | F14: Les anomalies sont trouvées et corrigées avant la clôture du mois.
A15: Classer les documents justificatifs | B15: k3 | C15: =IF(B15="","Rôle du poste",IFERROR(INDEX(Missions!$B$5:$B$21,MATCH(B15,Missions!$A$5:$A$21,0)),"ID inconnu")) -> Contrôle et suivi financier | D15: Ranger les preuves : factures, reçus, feuilles de présence, bons de commande. | E15: • Adopter une méthode simple (par mois, par partenaire ou par type) et s’y tenir. • Cela permet de justifier un chiffre en cas de question ou de contrôle. | F15: Chaque chiffre important a sa preuve, facile à retrouver.
A16: Établir les tableaux de bord mensuels en lien avec le cadre intermédiaire financier | B16: k4 | C16: =IF(B16="","Rôle du poste",IFERROR(INDEX(Missions!$B$5:$B$21,MATCH(B16,Missions!$A$5:$A$21,0)),"ID inconnu")) -> Contrôle et suivi financier | D16: Produire chaque mois une synthèse chiffrée de l’activité administrative. C’est ce que permet le tableau de bord du responsable administratif. | E16: • Récupérer les chiffres auprès du responsable financier. • Les mettre en forme et les comparer aux objectifs. • Les présenter à la direction. | F16: Le tableau est prêt à date fixe et la direction s’en sert pour décider. | G16: À confirmer : « Cadre intermédiaire financier » désigne probablement le responsable financier de niveau intermédiaire. À confirmer avec le Directeur Général.
A17: Suivre les règlements | B17: k5 | C17: =IF(B17="","Rôle du poste",IFERROR(INDEX(Missions!$B$5:$B$21,MATCH(B17,Missions!$A$5:$A$21,0)),"ID inconnu")) -> Contrôle et suivi financier | D17: Suivre les paiements. | E17: • Vérifier ce qui a été payé et ce qui ne l’est pas encore. • Repérer les retards, relancer ou alerter la direction. | F17: Aucun retard de paiement ne passe inaperçu. | G17: À confirmer : À préciser : cela concerne-t-il les paiements reçus des partenaires, ceux que l’entreprise doit payer, ou les deux ?
A18: Piloter l’équipe administrative | B18: e1 | C18: =IF(B18="","Rôle du poste",IFERROR(INDEX(Missions!$B$5:$B$21,MATCH(B18,Missions!$A$5:$A$21,0)),"ID inconnu")) -> Pilotage de l’équipe | D18: Diriger l’équipe. | E18: • Fixer les objectifs et les priorités. • Répartir le travail. • Faire un point régulier et suivre les résultats. | F18: L’équipe sait ce qu’on attend d’elle et atteint ses objectifs.
A19: Veiller au bon fonctionnement de l’équipe | B19: e2 | C19: =IF(B19="","Rôle du poste",IFERROR(INDEX(Missions!$B$5:$B$21,MATCH(B19,Missions!$A$5:$A$21,0)),"ID inconnu")) -> Pilotage de l’équipe | D19: S’assurer que l’équipe peut travailler dans de bonnes conditions. | E19: • Donner les outils et les consignes. • Résoudre les blocages. • Prévoir un remplacement en cas d’absence. • Garder une bonne ambiance de travail. | F19: Peu de blocages restent ouverts et le travail continue même en cas d’absence.
A20: Coordonner le travail auprès de ses collaborateurs | B20: e3 | C20: =IF(B20="","Rôle du poste",IFERROR(INDEX(Missions!$B$5:$B$21,MATCH(B20,Missions!$A$5:$A$21,0)),"ID inconnu")) -> Pilotage de l’équipe | D20: Faire en sorte que chacun sache quoi faire, et quand. | E20: • Transmettre les demandes de la direction. • Éviter qu’une tâche soit faite deux fois ou oubliée. • Faire circuler l’information. | F20: Les tâches s’enchaînent sans doublon ni oubli.
A21: Chargé de la gestion administrative | C21: =IF(B21="","Rôle du poste",IFERROR(INDEX(Missions!$B$5:$B$21,MATCH(B21,Missions!$A$5:$A$21,0)),"ID inconnu")) -> Rôle du poste | D21: C’est l’intitulé du rôle : cette personne tient l’administration de l’entreprise en ordre. | E21: • Les dossiers, les courriers, les contrats et les rendez-vous passent par elle, ou sous son contrôle. | F21: Personne ne cherche un document et aucune échéance n’est ratée.
A22: Effectue le traitement administratif de dossiers (prise de rendez-vous, rédaction du courrier, classement des dossiers, saisie de documents ou du budget). | B22: g2 | C22: =IF(B22="","Rôle du poste",IFERROR(INDEX(Missions!$B$5:$B$21,MATCH(B22,Missions!$A$5:$A$21,0)),"ID inconnu")) -> Gestion administrative | D22: C’est le travail courant, avec cinq tâches précises. | E22: • Prendre les rendez-vous et tenir l’agenda. • Rédiger les courriers et les réponses officielles. • Classer les dossiers, en papier et en numérique. • Saisir les documents dans les fichiers de l’entreprise. • Saisir le budget : entrer les montants prévus et dépensés. | F22: Le courrier part à temps et le budget est à jour.
A23: Accomplir toutes autres tâches qui lui seront confiées par le Directeur Général | B23: d1 | C23: =IF(B23="","Rôle du poste",IFERROR(INDEX(Missions!$B$5:$B$21,MATCH(B23,Missions!$A$5:$A$21,0)),"ID inconnu")) -> Demandes de la Direction | D23: C’est une clause ouverte : le Directeur Général peut ajouter des tâches liées au poste. | E23: • Noter chaque demande : date, contenu, échéance. • Cela évite les oublis et permet de montrer ce qui a été fait. | F23: Les demandes sont traitées dans les délais. | G23: Conseil : Pour une tâche importante ou inhabituelle, demandez une confirmation écrite. Cette clause couvre normalement des tâches cohérentes avec le poste ; les limites exactes dépendent du contrat de travail.
A25: PETIT LEXIQUE
A26: Convention | B26: Accord écrit avec un partenaire : qui fait quoi, pendant combien de temps, à quelles conditions.
A27: Contrat | B27: Accord qui engage l’entreprise, avec un client, un fournisseur ou un salarié.
A28: Avenant | B28: Document qui modifie un accord existant (durée, montant, date) sans tout refaire.
A29: Protocole | B29: Document qui fixe les règles de collaboration avec un partenaire.
A30: Émargement | B30: Feuille de présence signée par les personnes présentes à une séance, une formation ou une activité.
A31: Justificatif | B31: Preuve d’une dépense ou d’une activité : facture, reçu, bon de commande, feuille de présence.
A32: Anomalie | B32: Erreur, doublon, oubli ou montant qui paraît étrange dans une saisie.
A34: À CLARIFIER AVEC LE DIRECTEUR GÉNÉRAL
A35: 1. Qui est exactement le « cadre intermédiaire financier » (ligne « Établir les tableaux de bord mensuels ») ?
A36: 2. Que recouvre « règlements » (ligne « Suivre les règlements ») : les encaissements, les paiements, ou les deux ?
A37: 3. Quelles sont les limites de la dernière clause (« toutes autres tâches confiées par le Directeur Général ») ?
